smartgraph/__init__.py
smartgraph/components/__init__.py
smartgraph/components/branching_component.py
smartgraph/components/completion_component.py
smartgraph/components/human_in_the_loop.py
smartgraph/components/input_handlers.py
smartgraph/components/processing.py
smartgraph/core.py
smartgraph/exceptions.py
smartgraph/graph_visualizer.py
smartgraph/logging.py
smartgraph/tools/__init__.py
smartgraph/tools/base_toolkit.py
smartgraph/tools/duck_memory_toolkit.py
smartgraph/tools/duckduckgo_toolkit.py
smartgraph/tools/memory_toolkit.py
smartgraph/tools/tavily_toolkit.py
smartgraph/tools/weather_toolkit.py
smartgraph/utils.py
smartgraph-0.2.0.dist-info/LICENSE
smartgraph-0.2.0.dist-info/METADATA
smartgraph-0.2.0.dist-info/WHEEL
smartgraph-0.2.0.dist-info/RECORD
