Metadata-Version: 2.1
Name: smartgraph
Version: 0.2.0
Summary: A Python library for building stateful, multi-component applications with Large Language Models (LLMs).
License: MIT
Author: Jeblister
Requires-Python: >=3.11,<4.0
Classifier: License :: OSI Approved :: MIT License
Classifier: Programming Language :: Python :: 3
Classifier: Programming Language :: Python :: 3.11
Requires-Dist: aiofiles (>=24.1.0,<25.0.0)
Requires-Dist: anthropic (>=0.30.0,<0.31.0)
Requires-Dist: asyncio (>=3.4.3,<4.0.0)
Requires-Dist: duckdb (>=1.0.0,<2.0.0)
Requires-Dist: duckduckgo-search (>=6.2.0,<7.0.0)
Requires-Dist: jsonpickle (>=3.2.2,<4.0.0)
Requires-Dist: litellm (>=1.41.15,<2.0.0)
Requires-Dist: matplotlib (>=3.9.1,<4.0.0)
Requires-Dist: pydantic (>=2.8.2,<3.0.0)
Requires-Dist: python-dotenv (>=1.0.1,<2.0.0)
Requires-Dist: reactivex (>=4.0.4,<5.0.0)
Requires-Dist: requests (>=2.32.3,<3.0.0)
Requires-Dist: rich (>=13.7.1,<14.0.0)
Requires-Dist: tavily-python (>=0.3.5,<0.4.0)
Requires-Dist: typing-extensions (>=4.12.2,<5.0.0)
